{"__libc_csu_init": {"callee": ["_init"], "caller": ["_start"]}, "_init": {"callee": [], "caller": ["__libc_csu_init"]}, "pr_version": {"callee": ["<EXTERNAL>::pr2serr"], "caller": ["main"]}, "strpbrk": {"callee": [], "caller": ["strpbrk"]}, "usage": {"callee": ["<EXTERNAL>::pr2serr"], "caller": ["main"]}, "get_scsi_pt_result_category": {"callee": [], "caller": ["get_scsi_pt_result_category"]}, "main": {"callee": ["<EXTERNAL>::memset", "parse_cmd_line", "<EXTERNAL>::pr2serr", "pr_version", "usage", "usage", "<EXTERNAL>::scsi_pt_open_device", "<EXTERNAL>::safe_strerror", "<EXTERNAL>::pr2serr", "<EXTERNAL>::sg_convert_errno", "<EXTERNAL>::construct_scsi_pt_obj", "<EXTERNAL>::pr2serr", "<EXTERNAL>::sg_is_scsi_cdb", "fetch_dataout", "<EXTERNAL>::pr2serr", "<EXTERNAL>::set_scsi_pt_data_out", "sg_get_unaligned_le64", "sg_put_unaligned_le64", "sg_get_unaligned_le32", "sg_put_unaligned_le32", "<EXTERNAL>::sg_memalign", "<EXTERNAL>::pr2serr", "<EXTERNAL>::sg_convert_errno", "<EXTERNAL>::pr2serr", "<EXTERNAL>::set_scsi_pt_data_in", "sg_get_unaligned_le64", "sg_put_unaligned_le64", "sg_get_unaligned_le32", "sg_put_unaligned_le32", "<EXTERNAL>::pr2serr", "<EXTERNAL>::pr2serr", "<EXTERNAL>::pr2serr", "<EXTERNAL>::sg_get_command_name", "<EXTERNAL>::pr2serr", "<EXTERNAL>::pr2serr", "<EXTERNAL>::hex2stderr", "<EXTERNAL>::sg_get_nvme_opcode_name", "<EXTERNAL>::pr2serr", "<EXTERNAL>::set_scsi_pt_cdb", "<EXTERNAL>::pr2serr", "<EXTERNAL>::set_scsi_pt_sense", "<EXTERNAL>::do_scsi_pt", "<EXTERNAL>::pr2serr", "<EXTERNAL>::pr2serr", "<EXTERNAL>::get_scsi_pt_status_response", "<EXTERNAL>::sg_get_nvme_cmd_status_str", "<EXTERNAL>::pr2serr", "<EXTERNAL>::get_pt_result", "<EXTERNAL>::pr2serr", "<EXTERNAL>::get_scsi_pt_sense_len", "<EXTERNAL>::pr2serr", "<EXTERNAL>::hex2stderr", "<EXTERNAL>::pr2serr", "<EXTERNAL>::safe_strerror", "<EXTERNAL>::pr2serr", "<EXTERNAL>::get_scsi_pt_os_err", "<EXTERNAL>::safe_strerror", "<EXTERNAL>::pr2serr", "<EXTERNAL>::sg_convert_errno", "<EXTERNAL>::get_scsi_pt_sense_len", "<EXTERNAL>::get_scsi_pt_result_category", "<EXTERNAL>::sg_err_category_sense", "<EXTERNAL>::get_scsi_pt_transport_err_str", "<EXTERNAL>::pr2serr", "<EXTERNAL>::get_scsi_pt_os_err_str", "<EXTERNAL>::pr2serr", "<EXTERNAL>::pr2serr", "<EXTERNAL>::get_scsi_pt_status_response", "<EXTERNAL>::pr2serr", "<EXTERNAL>::sg_print_scsi_status", "<EXTERNAL>::pr2serr", "<EXTERNAL>::pr2serr", "<EXTERNAL>::pr2serr", "<EXTERNAL>::sg_print_sense", "<EXTERNAL>::pr2serr", "<EXTERNAL>::get_pt_result", "<EXTERNAL>::pr2serr", "<EXTERNAL>::pr2serr", "<EXTERNAL>::hex2stderr", "<EXTERNAL>::get_scsi_pt_resid", "<EXTERNAL>::pr2serr", "<EXTERNAL>::pr2serr", "<EXTERNAL>::pr2serr", "<EXTERNAL>::hex2stderr", "<EXTERNAL>::strlen", "<EXTERNAL>::pr2serr", "write_dataout", "<EXTERNAL>::sg_get_category_sense_str", "<EXTERNAL>::pr2serr", "<EXTERNAL>::free", "<EXTERNAL>::free", "<EXTERNAL>::destruct_scsi_pt_obj", "<EXTERNAL>::scsi_pt_close_device", "<EXTERNAL>::__stack_chk_fail"], "caller": ["_start"]}, "FUN_00002020": {"callee": [], "caller": []}, "fgets": {"callee": [], "caller": ["fgets"]}, "sg_get_unaligned_le32": {"callee": ["<EXTERNAL>::__stack_chk_fail"], "caller": ["main"]}, "strlen": {"callee": [], "caller": ["strlen"]}, "fopen64": {"callee": [], "caller": ["fopen64"]}, "get_scsi_pt_transport_err_str": {"callee": [], "caller": ["get_scsi_pt_transport_err_str"]}, "sg_get_num": {"callee": [], "caller": ["sg_get_num"]}, "safe_strerror": {"callee": [], "caller": ["safe_strerror"]}, "__errno_location": {"callee": [], "caller": ["__errno_location"]}, "sg_get_unaligned_be16": {"callee": ["__bswap_16", "<EXTERNAL>::__stack_chk_fail"], "caller": ["parse_cmd_line"]}, "sg_get_nvme_opcode_name": {"callee": [], "caller": ["sg_get_nvme_opcode_name"]}, "write": {"callee": [], "caller": ["write"]}, "frame_dummy": {"callee": [], "caller": ["__libc_csu_init"]}, "_ITM_registerTMCloneTable": {"callee": [], "caller": ["register_tm_clones"]}, "__cxa_finalize": {"callee": [], "caller": ["__cxa_finalize"]}, "read": {"callee": [], "caller": ["read"]}, "sg_err_category_sense": {"callee": [], "caller": ["sg_err_category_sense"]}, "set_scsi_pt_data_out": {"callee": [], "caller": ["set_scsi_pt_data_out"]}, "write_dataout": {"callee": ["<EXTERNAL>::strlen", "<EXTERNAL>::creat64", "<EXTERNAL>::__errno_location", "<EXTERNAL>::sg_convert_errno", "<EXTERNAL>::perror", "<EXTERNAL>::sg_set_binary_mode", "<EXTERNAL>::perror", "<EXTERNAL>::write", "<EXTERNAL>::__errno_location", "<EXTERNAL>::sg_convert_errno", "<EXTERNAL>::perror", "<EXTERNAL>::close"], "caller": ["main"]}, "__gmon_start__": {"callee": [], "caller": ["_init"]}, "set_scsi_pt_data_in": {"callee": [], "caller": ["set_scsi_pt_data_in"]}, "sg_get_category_sense_str": {"callee": [], "caller": ["sg_get_category_sense_str"]}, "get_scsi_pt_os_err_str": {"callee": [], "caller": ["get_scsi_pt_os_err_str"]}, "memset": {"callee": [], "caller": ["memset"]}, "hex2stderr": {"callee": [], "caller": ["hex2stderr"]}, "__libc_csu_fini": {"callee": [], "caller": ["_start"]}, "__isoc99_sscanf": {"callee": [], "caller": ["__isoc99_sscanf"]}, "strspn": {"callee": [], "caller": ["strspn"]}, "sg_memalign": {"callee": [], "caller": ["sg_memalign"]}, "pr2serr": {"callee": [], "caller": ["pr2serr"]}, "construct_scsi_pt_obj": {"callee": [], "caller": ["construct_scsi_pt_obj"]}, "scsi_pt_close_device": {"callee": [], "caller": ["scsi_pt_close_device"]}, "lseek64": {"callee": [], "caller": ["lseek64"]}, "__ctype_b_loc": {"callee": [], "caller": ["__ctype_b_loc"]}, "_start": {"callee": [], "caller": []}, "sg_is_scsi_cdb": {"callee": [], "caller": ["sg_is_scsi_cdb"]}, "do_scsi_pt": {"callee": [], "caller": ["do_scsi_pt"]}, "get_scsi_pt_resid": {"callee": [], "caller": ["get_scsi_pt_resid"]}, "sg_convert_errno": {"callee": [], "caller": ["sg_convert_errno"]}, "creat64": {"callee": [], "caller": ["creat64"]}, "__stack_chk_fail": {"callee": [], "caller": ["__stack_chk_fail"]}, "skip": {"callee": ["<EXTERNAL>::lseek64", "<EXTERNAL>::read", "<EXTERNAL>::__errno_location", "<EXTERNAL>::perror", "<EXTERNAL>::sg_convert_errno", "<EXTERNAL>::pr2serr", "<EXTERNAL>::__stack_chk_fail"], "caller": ["fetch_dataout"]}, "open64": {"callee": [], "caller": ["open64"]}, "sg_put_unaligned_le64": {"callee": [], "caller": ["main"]}, "printf": {"callee": [], "caller": ["printf"]}, "deregister_tm_clones": {"callee": [], "caller": ["__do_global_dtors_aux"]}, "sg_get_unaligned_le64": {"callee": ["<EXTERNAL>::__stack_chk_fail"], "caller": ["main"]}, "__libc_start_main": {"callee": [], "caller": ["_start"]}, "set_scsi_pt_sense": {"callee": [], "caller": ["set_scsi_pt_sense"]}, "__fxstat64": {"callee": [], "caller": ["fstat64"]}, "destruct_scsi_pt_obj": {"callee": [], "caller": ["destruct_scsi_pt_obj"]}, "sg_print_scsi_status": {"callee": [], "caller": ["sg_print_scsi_status"]}, "strtol": {"callee": [], "caller": ["strtol"]}, "scsi_pt_open_device": {"callee": [], "caller": ["scsi_pt_open_device"]}, "f2hex_arr": {"callee": ["<EXTERNAL>::strlen", "<EXTERNAL>::open64", "<EXTERNAL>::__errno_location", "<EXTERNAL>::safe_strerror", "<EXTERNAL>::pr2serr", "<EXTERNAL>::read", "<EXTERNAL>::pr2serr", "<EXTERNAL>::__errno_location", "<EXTERNAL>::safe_strerror", "<EXTERNAL>::pr2serr", "<EXTERNAL>::close", "fstat64", "<EXTERNAL>::read", "<EXTERNAL>::__errno_location", "<EXTERNAL>::safe_strerror", "<EXTERNAL>::pr2serr", "<EXTERNAL>::close", "<EXTERNAL>::close", "<EXTERNAL>::fopen64", "<EXTERNAL>::pr2serr", "<EXTERNAL>::fgets", "<EXTERNAL>::strlen", "<EXTERNAL>::__ctype_b_loc", "<EXTERNAL>::__isoc99_sscanf", "<EXTERNAL>::pr2serr", "<EXTERNAL>::strspn", "<EXTERNAL>::strspn", "<EXTERNAL>::pr2serr", "<EXTERNAL>::__isoc99_sscanf", "<EXTERNAL>::pr2serr", "<EXTERNAL>::pr2serr", "<EXTERNAL>::__ctype_b_loc", "<EXTERNAL>::__ctype_b_loc", "<EXTERNAL>::__ctype_b_loc", "<EXTERNAL>::__ctype_b_loc", "<EXTERNAL>::__isoc99_sscanf", "<EXTERNAL>::pr2serr", "<EXTERNAL>::strlen", "<EXTERNAL>::pr2serr", "<EXTERNAL>::strpbrk", "<EXTERNAL>::strspn", "<EXTERNAL>::pr2serr", "<EXTERNAL>::fclose", "<EXTERNAL>::fclose", "<EXTERNAL>::__stack_chk_fail"], "caller": ["parse_cmd_line"]}, "_ITM_deregisterTMCloneTable": {"callee": [], "caller": ["deregister_tm_clones"]}, "free": {"callee": [], "caller": ["free"]}, "close": {"callee": [], "caller": ["close"]}, "register_tm_clones": {"callee": [], "caller": ["frame_dummy"]}, "getopt_long": {"callee": [], "caller": ["getopt_long"]}, "fclose": {"callee": [], "caller": ["fclose"]}, "get_scsi_pt_status_response": {"callee": [], "caller": ["get_scsi_pt_status_response"]}, "get_pt_result": {"callee": [], "caller": ["get_pt_result"]}, "get_scsi_pt_sense_len": {"callee": [], "caller": ["get_scsi_pt_sense_len"]}, "sg_set_binary_mode": {"callee": [], "caller": ["sg_set_binary_mode"]}, "sg_put_unaligned_le32": {"callee": [], "caller": ["main"]}, "fetch_dataout": {"callee": ["<EXTERNAL>::open64", "<EXTERNAL>::__errno_location", "<EXTERNAL>::sg_convert_errno", "<EXTERNAL>::perror", "<EXTERNAL>::sg_set_binary_mode", "<EXTERNAL>::__errno_location", "<EXTERNAL>::perror", "skip", "<EXTERNAL>::sg_memalign", "<EXTERNAL>::pr2serr", "<EXTERNAL>::sg_convert_errno", "<EXTERNAL>::read", "<EXTERNAL>::__errno_location", "<EXTERNAL>::sg_convert_errno", "<EXTERNAL>::perror", "<EXTERNAL>::pr2serr", "<EXTERNAL>::close", "<EXTERNAL>::free"], "caller": ["main"]}, "sg_get_nvme_cmd_status_str": {"callee": [], "caller": ["sg_get_nvme_cmd_status_str"]}, "get_scsi_pt_os_err": {"callee": [], "caller": ["get_scsi_pt_os_err"]}, "__bswap_16": {"callee": [], "caller": ["sg_get_unaligned_be16"]}, "sg_get_command_name": {"callee": [], "caller": ["sg_get_command_name"]}, "puts": {"callee": [], "caller": ["puts"]}, "fstat64": {"callee": [], "caller": ["f2hex_arr"]}, "set_scsi_pt_cdb": {"callee": [], "caller": ["set_scsi_pt_cdb"]}, "__do_global_dtors_aux": {"callee": ["<EXTERNAL>::__cxa_finalize", "deregister_tm_clones"], "caller": ["__libc_csu_init"]}, "parse_cmd_line": {"callee": ["<EXTERNAL>::getopt_long", "<EXTERNAL>::pr2serr", "<EXTERNAL>::sg_get_num", "<EXTERNAL>::pr2serr", "<EXTERNAL>::pr2serr", "<EXTERNAL>::sg_get_num", "<EXTERNAL>::pr2serr", "<EXTERNAL>::sg_get_num", "<EXTERNAL>::pr2serr", "<EXTERNAL>::sg_get_num", "<EXTERNAL>::pr2serr", "<EXTERNAL>::pr2serr", "<EXTERNAL>::strtol", "<EXTERNAL>::pr2serr", "<EXTERNAL>::pr2serr", "f2hex_arr", "<EXTERNAL>::pr2serr", "<EXTERNAL>::hex2stderr", "<EXTERNAL>::pr2serr", "<EXTERNAL>::sg_is_scsi_cdb", "sg_get_unaligned_be16", "<EXTERNAL>::puts", "<EXTERNAL>::sg_get_opcode_sa_name", "<EXTERNAL>::printf", "<EXTERNAL>::sg_get_nvme_opcode_name", "<EXTERNAL>::printf", "<EXTERNAL>::__stack_chk_fail"], "caller": ["main"]}, "_fini": {"callee": [], "caller": []}, "perror": {"callee": [], "caller": ["perror"]}, "sg_get_opcode_sa_name": {"callee": [], "caller": ["sg_get_opcode_sa_name"]}, "sg_print_sense": {"callee": [], "caller": ["sg_print_sense"]}}