{"version_etc_arn": {"callee": ["<EXTERNAL>::fprintf", "<EXTERNAL>::fprintf", "<EXTERNAL>::gettext", "<EXTERNAL>::fprintf", "<EXTERNAL>::gettext", "<EXTERNAL>::fputs_unlocked", "<EXTERNAL>::abort", "<EXTERNAL>::gettext", "<EXTERNAL>::fprintf", "<EXTERNAL>::gettext", "<EXTERNAL>::fprintf", "<EXTERNAL>::gettext", "<EXTERNAL>::fprintf", "<EXTERNAL>::gettext", "<EXTERNAL>::fprintf", "<EXTERNAL>::gettext", "<EXTERNAL>::fprintf", "<EXTERNAL>::gettext", "<EXTERNAL>::fprintf", "<EXTERNAL>::gettext", "<EXTERNAL>::fprintf", "<EXTERNAL>::gettext", "<EXTERNAL>::fprintf", "<EXTERNAL>::gettext", "<EXTERNAL>::fprintf", "<EXTERNAL>::gettext", "<EXTERNAL>::fprintf"], "caller": ["version_etc_va", "version_etc_ar"]}, "strchr": {"callee": [], "caller": ["strchr"]}, "rpl_fclose": {"callee": ["<EXTERNAL>::fileno", "<EXTERNAL>::fclose", "<EXTERNAL>::__freading", "<EXTERNAL>::fileno", "<EXTERNAL>::lseek", "rpl_fflush", "<EXTERNAL>::__errno_location", "<EXTERNAL>::fclose", "<EXTERNAL>::__errno_location"], "caller": ["ofile_open", "closeout", "lines_rr", "close_stream"]}, "fwrite_unlocked": {"callee": [], "caller": ["fwrite_unlocked"]}, "to_uchar": {"callee": [], "caller": ["main"]}, "strncmp": {"callee": [], "caller": ["strncmp"]}, "xnrealloc": {"callee": ["xalloc_die", "xrealloc"], "caller": []}, "quote": {"callee": ["quote_n"], "caller": ["main", "xnumtoumax"]}, "emit_bug_reporting_address": {"callee": ["<EXTERNAL>::gettext", "<EXTERNAL>::printf", "<EXTERNAL>::gettext", "<EXTERNAL>::printf", "<EXTERNAL>::gettext", "<EXTERNAL>::fputs_unlocked"], "caller": []}, "xmalloc": {"callee": ["<EXTERNAL>::malloc", "xalloc_die"], "caller": ["xcharalloc", "xzalloc", "main", "xnmalloc", "xmemdup"]}, "clone_quoting_options": {"callee": ["<EXTERNAL>::__errno_location", "xmemdup", "<EXTERNAL>::__errno_location"], "caller": []}, "gettext": {"callee": [], "caller": ["gettext"]}, "quotearg_char_mem": {"callee": ["set_char_quoting", "quotearg_n_options", "<EXTERNAL>::__stack_chk_fail"], "caller": ["quotearg_colon_mem", "quotearg_char"]}, "frame_dummy": {"callee": [], "caller": ["__libc_csu_init"]}, "_ITM_registerTMCloneTable": {"callee": [], "caller": ["register_tm_clones"]}, "quotearg_n_style_colon": {"callee": ["quoting_options_from_style", "set_char_quoting", "quotearg_n_options", "<EXTERNAL>::__stack_chk_fail"], "caller": ["create", "ofile_open", "cwrite", "lines_chunk_split", "main", "lines_split", "bytes_chunk_extract", "closeout", "lines_rr", "line_bytes_split", "bytes_split"]}, "__gmon_start__": {"callee": [], "caller": ["_init"]}, "io_blksize": {"callee": [], "caller": ["main"]}, "lines_split": {"callee": ["safe_read", "quotearg_n_style_colon", "<EXTERNAL>::__errno_location", "<EXTERNAL>::error", "<EXTERNAL>::memchr", "cwrite", "cwrite"], "caller": ["main"]}, "quote_mem": {"callee": ["quote_n_mem"], "caller": []}, "fileno": {"callee": [], "caller": ["fileno"]}, "sigemptyset": {"callee": [], "caller": ["sigemptyset"]}, "mbrtowc": {"callee": [], "caller": ["mbrtowc"]}, "dup2": {"callee": [], "caller": ["dup2"]}, "execl": {"callee": [], "caller": ["execl"]}, "xstrtoumax": {"callee": ["<EXTERNAL>::__assert_fail", "<EXTERNAL>::__errno_location", "<EXTERNAL>::__ctype_b_loc", "<EXTERNAL>::strtoumax", "<EXTERNAL>::strchr", "<EXTERNAL>::__errno_location", "<EXTERNAL>::__errno_location", "<EXTERNAL>::strchr", "<EXTERNAL>::strchr", "bkm_scale", "bkm_scale", "bkm_scale_by_power", "bkm_scale_by_power", "bkm_scale_by_power", "bkm_scale_by_power", "bkm_scale_by_power", "bkm_scale_by_power", "bkm_scale", "bkm_scale_by_power", "bkm_scale_by_power", "<EXTERNAL>::__stack_chk_fail"], "caller": ["set_suffix_length", "xnumtoumax"]}, "__libc_current_sigrtmax": {"callee": [], "caller": ["__libc_current_sigrtmax"]}, "setlocale": {"callee": [], "caller": ["setlocale"]}, "c_toupper": {"callee": [], "caller": []}, "bad_cast": {"callee": [], "caller": ["main"]}, "fcntl": {"callee": [], "caller": ["fcntl"]}, "mbsinit": {"callee": [], "caller": ["mbsinit"]}, "quotearg_free": {"callee": ["<EXTERNAL>::free", "<EXTERNAL>::free", "<EXTERNAL>::free"], "caller": []}, "quotearg_mem": {"callee": ["quotearg_n_mem"], "caller": []}, "deregister_tm_clones": {"callee": [], "caller": ["__do_global_dtors_aux"]}, "ptr_align": {"callee": [], "caller": ["main"]}, "__libc_start_main": {"callee": [], "caller": ["_start"]}, "set_suffix_length": {"callee": ["xstrtoumax", "<EXTERNAL>::strlen", "<EXTERNAL>::gettext", "<EXTERNAL>::error", "<EXTERNAL>::__stack_chk_fail"], "caller": ["main"]}, "quotearg_custom": {"callee": ["quotearg_n_custom"], "caller": []}, "free": {"callee": [], "caller": ["free"]}, "close": {"callee": [], "caller": ["close"]}, "getenv": {"callee": [], "caller": ["getenv"]}, "rpl_fseeko": {"callee": ["<EXTERNAL>::fileno", "<EXTERNAL>::lseek", "<EXTERNAL>::fseeko"], "caller": ["clear_ungetc_buffer_preserving_position"]}, "quote_n_mem": {"callee": ["quotearg_n_options"], "caller": ["quote_mem", "quote_n"]}, "xstrdup": {"callee": ["<EXTERNAL>::strlen", "xmemdup"], "caller": ["lines_rr"]}, "c_ispunct": {"callee": [], "caller": []}, "fstat": {"callee": [], "caller": ["create", "main"]}, "fprintf": {"callee": [], "caller": ["fprintf"]}, "memcpy": {"callee": [], "caller": ["memcpy"]}, "close_stdout_set_ignore_EPIPE": {"callee": [], "caller": []}, "iswprint": {"callee": [], "caller": ["iswprint"]}, "ftruncate": {"callee": [], "caller": ["ftruncate"]}, "c_isspace": {"callee": [], "caller": []}, "open": {"callee": [], "caller": ["open"]}, "quotearg_n_custom_mem": {"callee": ["set_custom_quoting", "quotearg_n_options", "<EXTERNAL>::__stack_chk_fail"], "caller": ["quotearg_custom_mem", "quotearg_n_custom"]}, "_init": {"callee": [], "caller": ["__libc_csu_init"]}, "set_quoting_flags": {"callee": [], "caller": []}, "realloc": {"callee": [], "caller": ["realloc"]}, "nl_langinfo": {"callee": [], "caller": ["nl_langinfo"]}, "sprintf": {"callee": [], "caller": ["sprintf"]}, "x2realloc": {"callee": ["x2nrealloc"], "caller": []}, "strlen": {"callee": [], "caller": ["strlen"]}, "memcmp": {"callee": [], "caller": ["memcmp"]}, "input_file_size": {"callee": ["<EXTERNAL>::lseek", "<EXTERNAL>::__errno_location", "<EXTERNAL>::__errno_location", "safe_read", "<EXTERNAL>::__errno_location", "usable_st_size", "<EXTERNAL>::lseek", "<EXTERNAL>::lseek", "<EXTERNAL>::__errno_location"], "caller": ["main"]}, "quotearg_n_style_mem": {"callee": ["quoting_options_from_style", "quotearg_n_options", "<EXTERNAL>::__stack_chk_fail"], "caller": ["quotearg_style_mem"]}, "_exit": {"callee": [], "caller": ["_exit"]}, "emit_stdin_note": {"callee": ["<EXTERNAL>::gettext", "<EXTERNAL>::fputs_unlocked"], "caller": ["usage"]}, "xdectoumax": {"callee": ["xnumtoumax"], "caller": ["main", "parse_chunk"]}, "bkm_scale_by_power": {"callee": ["bkm_scale"], "caller": ["xstrtoumax"]}, "xrealloc": {"callee": ["<EXTERNAL>::free", "<EXTERNAL>::realloc", "xalloc_die"], "caller": ["next_file_name", "xnrealloc", "quotearg_n_options", "x2nrealloc", "line_bytes_split"]}, "__gl_setmode_check": {"callee": [], "caller": ["set_binary_mode"]}, "emit_size_note": {"callee": ["<EXTERNAL>::gettext", "<EXTERNAL>::fputs_unlocked"], "caller": ["usage"]}, "close_stdout": {"callee": ["close_stream", "<EXTERNAL>::__errno_location", "<EXTERNAL>::gettext", "quotearg_colon", "<EXTERNAL>::__errno_location", "<EXTERNAL>::error", "<EXTERNAL>::__errno_location", "<EXTERNAL>::error", "<EXTERNAL>::_exit", "close_stream", "<EXTERNAL>::_exit"], "caller": ["main"]}, "version_etc_ar": {"callee": ["version_etc_arn"], "caller": []}, "strtoumax": {"callee": [], "caller": ["strtoumax"]}, "__gl_setmode": {"callee": [], "caller": ["set_binary_mode"]}, "str2sig": {"callee": ["str2signum"], "caller": []}, "c_isxdigit": {"callee": [], "caller": []}, "__libc_csu_fini": {"callee": [], "caller": ["_start"]}, "abort": {"callee": [], "caller": ["abort"]}, "usable_st_size": {"callee": [], "caller": ["input_file_size"]}, "version_etc": {"callee": ["version_etc_va", "<EXTERNAL>::__stack_chk_fail"], "caller": ["main"]}, "ignorable": {"callee": [], "caller": ["cwrite", "bytes_chunk_extract", "closeout", "lines_rr"]}, "fseeko": {"callee": [], "caller": ["fseeko"]}, "lseek": {"callee": [], "caller": ["lseek"]}, "memrchr": {"callee": [], "caller": ["memrchr"]}, "quotearg_n_mem": {"callee": ["quotearg_n_options"], "caller": ["quotearg_mem"]}, "__stack_chk_fail": {"callee": [], "caller": ["__stack_chk_fail"]}, "calloc": {"callee": [], "caller": ["calloc"]}, "base_len": {"callee": ["<EXTERNAL>::strlen"], "caller": []}, "printf": {"callee": [], "caller": ["printf"]}, "emit_ancillary_info": {"callee": ["<EXTERNAL>::strcmp", "<EXTERNAL>::gettext", "<EXTERNAL>::printf", "<EXTERNAL>::setlocale", "<EXTERNAL>::strncmp", "<EXTERNAL>::gettext", "<EXTERNAL>::printf", "<EXTERNAL>::gettext", "<EXTERNAL>::printf", "<EXTERNAL>::gettext", "<EXTERNAL>::printf", "<EXTERNAL>::__stack_chk_fail"], "caller": ["usage"]}, "version_etc_va": {"callee": ["version_etc_arn", "<EXTERNAL>::__stack_chk_fail"], "caller": ["version_etc"]}, "xzalloc": {"callee": ["xmalloc", "<EXTERNAL>::memset"], "caller": []}, "umaxtostr": {"callee": [], "caller": ["main"]}, "__fxstat": {"callee": [], "caller": ["fstat"]}, "__cxa_atexit": {"callee": [], "caller": ["atexit"]}, "gettext_quote": {"callee": ["<EXTERNAL>::gettext", "locale_charset", "c_strcasecmp", "c_strcasecmp"], "caller": ["quotearg_buffer_restyled"]}, "fclose": {"callee": [], "caller": ["fclose"]}, "__ctype_get_mb_cur_max": {"callee": [], "caller": ["__ctype_get_mb_cur_max"]}, "quotearg_n_style": {"callee": ["quoting_options_from_style", "quotearg_n_options", "<EXTERNAL>::__stack_chk_fail"], "caller": ["quotearg_style"]}, "cwrite": {"callee": ["closeout", "next_file_name", "create", "quotearg_n_style_colon", "<EXTERNAL>::__errno_location", "<EXTERNAL>::error", "full_write", "<EXTERNAL>::__errno_location", "ignorable", "quotearg_n_style_colon", "<EXTERNAL>::__errno_location", "<EXTERNAL>::error"], "caller": ["lines_chunk_split", "lines_split", "line_bytes_split", "bytes_split"]}, "fork": {"callee": [], "caller": ["fork"]}, "quote_n": {"callee": ["quote_n_mem"], "caller": ["quote"]}, "set_binary_mode": {"callee": ["__gl_setmode_check", "__gl_setmode"], "caller": ["xset_binary_mode"]}, "quotearg_alloc": {"callee": ["quotearg_alloc_mem"], "caller": []}, "close_stdout_set_file_name": {"callee": [], "caller": []}, "parse_chunk": {"callee": ["<EXTERNAL>::gettext", "xdectoumax", "<EXTERNAL>::gettext", "xdectoumax"], "caller": ["main"]}, "safe_write": {"callee": ["<EXTERNAL>::write", "<EXTERNAL>::__errno_location", "<EXTERNAL>::__errno_location"], "caller": ["full_write"]}, "ofile_open": {"callee": ["create", "open_safer", "<EXTERNAL>::__errno_location", "<EXTERNAL>::__errno_location", "quotearg_n_style_colon", "<EXTERNAL>::__errno_location", "<EXTERNAL>::error", "quotearg_n_style_colon", "<EXTERNAL>::__errno_location", "<EXTERNAL>::error", "rpl_fclose", "quotearg_n_style_colon", "<EXTERNAL>::__errno_location", "<EXTERNAL>::error", "<EXTERNAL>::fdopen", "quotearg_n_style_colon", "<EXTERNAL>::__errno_location", "<EXTERNAL>::error"], "caller": ["lines_rr"]}, "__libc_csu_init": {"callee": ["_init"], "caller": ["_start"]}, "bytes_chunk_extract": {"callee": ["<EXTERNAL>::__assert_fail", "<EXTERNAL>::memmove", "<EXTERNAL>::lseek", "quotearg_n_style_colon", "<EXTERNAL>::__errno_location", "<EXTERNAL>::error", "safe_read", "quotearg_n_style_colon", "<EXTERNAL>::__errno_location", "<EXTERNAL>::error", "full_write", "<EXTERNAL>::__errno_location", "ignorable", "quotearg_n_style_colon", "<EXTERNAL>::__errno_location", "<EXTERNAL>::error"], "caller": ["main"]}, "c_isdigit": {"callee": [], "caller": []}, "str2signum": {"callee": ["<EXTERNAL>::strtol", "<EXTERNAL>::strcmp", "<EXTERNAL>::__libc_current_sigrtmin", "<EXTERNAL>::__libc_current_sigrtmax", "<EXTERNAL>::strncmp", "<EXTERNAL>::strtol", "<EXTERNAL>::strncmp", "<EXTERNAL>::strtol", "<EXTERNAL>::__stack_chk_fail"], "caller": ["str2sig"]}, "usage": {"callee": ["<EXTERNAL>::gettext", "<EXTERNAL>::fprintf", "<EXTERNAL>::gettext", "<EXTERNAL>::printf", "<EXTERNAL>::gettext", "<EXTERNAL>::fputs_unlocked", "emit_stdin_note", "emit_mandatory_arg_note", "<EXTERNAL>::gettext", "<EXTERNAL>::fprintf", "<EXTERNAL>::gettext", "<EXTERNAL>::fputs_unlocked", "<EXTERNAL>::gettext", "<EXTERNAL>::fputs_unlocked", "<EXTERNAL>::gettext", "<EXTERNAL>::fputs_unlocked", "emit_size_note", "<EXTERNAL>::gettext", "<EXTERNAL>::fputs_unlocked", "emit_ancillary_info", "<EXTERNAL>::exit"], "caller": ["main"]}, "quoting_options_from_style": {"callee": ["<EXTERNAL>::abort", "<EXTERNAL>::__stack_chk_fail"], "caller": ["quotearg_n_style", "quotearg_n_style_colon", "quotearg_n_style_mem"]}, "strcpy": {"callee": [], "caller": ["strcpy"]}, "rpl_mbrtowc": {"callee": ["<EXTERNAL>::mbrtowc", "hard_locale", "<EXTERNAL>::__stack_chk_fail"], "caller": ["quotearg_buffer_restyled"]}, "c_isgraph": {"callee": [], "caller": []}, "write": {"callee": [], "caller": ["write"]}, "quotearg_buffer_restyled": {"callee": ["<EXTERNAL>::__ctype_get_mb_cur_max", "gettext_quote", "gettext_quote", "<EXTERNAL>::strlen", "<EXTERNAL>::abort", "<EXTERNAL>::strlen", "<EXTERNAL>::memcmp", "<EXTERNAL>::__ctype_b_loc", "<EXTERNAL>::memset", "<EXTERNAL>::strlen", "rpl_mbrtowc", "<EXTERNAL>::iswprint", "<EXTERNAL>::mbsinit", "quotearg_buffer_restyled", "quotearg_buffer_restyled", "<EXTERNAL>::__stack_chk_fail"], "caller": ["quotearg_buffer_restyled", "quotearg_buffer", "quotearg_n_options", "quotearg_alloc_mem"]}, "hard_locale": {"callee": ["<EXTERNAL>::setlocale", "<EXTERNAL>::strcmp", "<EXTERNAL>::strcmp"], "caller": ["rpl_mbrtowc"]}, "__cxa_finalize": {"callee": [], "caller": ["__cxa_finalize"]}, "__libc_current_sigrtmin": {"callee": [], "caller": ["__libc_current_sigrtmin"]}, "set_quoting_style": {"callee": [], "caller": []}, "textdomain": {"callee": [], "caller": ["textdomain"]}, "xmemdup": {"callee": ["xmalloc", "<EXTERNAL>::memcpy"], "caller": ["xstrdup", "clone_quoting_options"]}, "getpagesize": {"callee": [], "caller": ["getpagesize"]}, "get_quoting_style": {"callee": [], "caller": []}, "exit": {"callee": [], "caller": ["exit"]}, "ferror_unlocked": {"callee": [], "caller": ["ferror_unlocked"]}, "locale_charset": {"callee": ["<EXTERNAL>::nl_langinfo"], "caller": ["gettext_quote"]}, "set_program_name": {"callee": ["<EXTERNAL>::fwrite", "<EXTERNAL>::abort", "<EXTERNAL>::strrchr", "<EXTERNAL>::strncmp", "<EXTERNAL>::strncmp"], "caller": ["main"]}, "strspn": {"callee": [], "caller": ["strspn"]}, "quotearg_buffer": {"callee": ["<EXTERNAL>::__errno_location", "quotearg_buffer_restyled", "<EXTERNAL>::__errno_location"], "caller": []}, "quotearg_colon": {"callee": ["quotearg_char"], "caller": ["close_stdout"]}, "rpl_fflush": {"callee": ["<EXTERNAL>::__freading", "<EXTERNAL>::fflush", "clear_ungetc_buffer_preserving_position", "<EXTERNAL>::fflush"], "caller": ["rpl_fclose"]}, "__assert_fail": {"callee": [], "caller": ["__assert_fail"]}, "bindtextdomain": {"callee": [], "caller": ["bindtextdomain"]}, "set_char_quoting": {"callee": [], "caller": ["quotearg_char_mem", "quotearg_n_style_colon"]}, "quotearg_n": {"callee": ["quotearg_n_options"], "caller": ["quotearg"]}, "close_stream": {"callee": ["<EXTERNAL>::__fpending", "<EXTERNAL>::ferror_unlocked", "rpl_fclose", "<EXTERNAL>::__errno_location", "<EXTERNAL>::__errno_location"], "caller": ["close_stdout"]}, "quotearg_colon_mem": {"callee": ["quotearg_char_mem"], "caller": []}, "setenv": {"callee": [], "caller": ["setenv"]}, "sig2str": {"callee": ["<EXTERNAL>::strcpy", "<EXTERNAL>::__libc_current_sigrtmin", "<EXTERNAL>::__libc_current_sigrtmax", "<EXTERNAL>::sprintf"], "caller": ["closeout"]}, "xcalloc": {"callee": ["<EXTERNAL>::calloc", "xalloc_die"], "caller": ["next_file_name"]}, "xnumtoumax": {"callee": ["xstrtoumax", "<EXTERNAL>::__errno_location", "<EXTERNAL>::__errno_location", "<EXTERNAL>::__errno_location", "<EXTERNAL>::__errno_location", "quote", "<EXTERNAL>::__errno_location", "<EXTERNAL>::__errno_location", "<EXTERNAL>::error", "<EXTERNAL>::__stack_chk_fail"], "caller": ["xdectoumax"]}, "strtol": {"callee": [], "caller": ["strtol"]}, "clear_ungetc_buffer_preserving_position": {"callee": ["rpl_fseeko"], "caller": ["rpl_fflush"]}, "_ITM_deregisterTMCloneTable": {"callee": [], "caller": ["deregister_tm_clones"]}, "xnmalloc": {"callee": ["xalloc_die", "xmalloc"], "caller": ["lines_rr"]}, "quotearg_char": {"callee": ["quotearg_char_mem"], "caller": ["quotearg_colon"]}, "malloc": {"callee": [], "caller": ["malloc"]}, "c_tolower": {"callee": [], "caller": ["c_strcasecmp"]}, "getopt_long": {"callee": [], "caller": ["getopt_long"]}, "lines_rr": {"callee": ["xnmalloc", "next_file_name", "xstrdup", "safe_read", "quotearg_n_style_colon", "<EXTERNAL>::__errno_location", "<EXTERNAL>::error", "<EXTERNAL>::memchr", "full_write", "<EXTERNAL>::gettext", "<EXTERNAL>::__errno_location", "<EXTERNAL>::error", "<EXTERNAL>::fwrite_unlocked", "<EXTERNAL>::clearerr_unlocked", "<EXTERNAL>::gettext", "<EXTERNAL>::__errno_location", "<EXTERNAL>::error", "ofile_open", "full_write", "<EXTERNAL>::__errno_location", "ignorable", "quotearg_n_style_colon", "<EXTERNAL>::__errno_location", "<EXTERNAL>::error", "<EXTERNAL>::fwrite_unlocked", "<EXTERNAL>::__errno_location", "ignorable", "quotearg_n_style_colon", "<EXTERNAL>::__errno_location", "<EXTERNAL>::error", "<EXTERNAL>::__errno_location", "ignorable", "rpl_fclose", "quotearg_n_style_colon", "<EXTERNAL>::__errno_location", "<EXTERNAL>::error", "ofile_open", "closeout"], "caller": ["main"]}, "bytes_split": {"callee": ["<EXTERNAL>::lseek", "safe_read", "quotearg_n_style_colon", "<EXTERNAL>::__errno_location", "<EXTERNAL>::error", "cwrite", "cwrite", "cwrite"], "caller": ["main"]}, "quotearg_style": {"callee": ["quotearg_n_style"], "caller": ["create", "main"]}, "fd_reopen": {"callee": ["<EXTERNAL>::open", "<EXTERNAL>::dup2", "<EXTERNAL>::__errno_location", "<EXTERNAL>::close", "<EXTERNAL>::__errno_location"], "caller": ["main"]}, "sigprocmask": {"callee": [], "caller": ["sigprocmask"]}, "closeout": {"callee": ["rpl_fclose", "<EXTERNAL>::__errno_location", "ignorable", "quotearg_n_style_colon", "<EXTERNAL>::__errno_location", "<EXTERNAL>::error", "<EXTERNAL>::close", "quotearg_n_style_colon", "<EXTERNAL>::__errno_location", "<EXTERNAL>::error", "<EXTERNAL>::waitpid", "<EXTERNAL>::__errno_location", "<EXTERNAL>::gettext", "<EXTERNAL>::__errno_location", "<EXTERNAL>::error", "sig2str", "<EXTERNAL>::sprintf", "quotearg_n_style_colon", "<EXTERNAL>::gettext", "<EXTERNAL>::error", "quotearg_n_style_colon", "<EXTERNAL>::gettext", "<EXTERNAL>::error", "<EXTERNAL>::gettext", "<EXTERNAL>::error", "<EXTERNAL>::__stack_chk_fail"], "caller": ["cwrite", "main", "lines_rr"]}, "strrchr": {"callee": [], "caller": ["strrchr"]}, "quotearg_alloc_mem": {"callee": ["<EXTERNAL>::__errno_location", "quotearg_buffer_restyled", "xcharalloc", "quotearg_buffer_restyled", "<EXTERNAL>::__errno_location"], "caller": ["quotearg_alloc"]}, "bkm_scale": {"callee": [], "caller": ["bkm_scale_by_power", "xstrtoumax"]}, "memchr": {"callee": [], "caller": ["memchr"]}, "quotearg_style_mem": {"callee": ["quotearg_n_style_mem"], "caller": []}, "xalloc_die": {"callee": ["<EXTERNAL>::gettext", "<EXTERNAL>::error", "<EXTERNAL>::abort"], "caller": ["next_file_name", "xmalloc", "xnrealloc", "quotearg_n_options", "x2nrealloc", "xrealloc", "line_bytes_split", "xnmalloc", "xcalloc"]}, "open_safer": {"callee": ["<EXTERNAL>::open", "fd_safer", "<EXTERNAL>::__stack_chk_fail"], "caller": ["create", "ofile_open"]}, "quotearg_n_custom": {"callee": ["quotearg_n_custom_mem"], "caller": ["quotearg_custom"]}, "waitpid": {"callee": [], "caller": ["waitpid"]}, "fflush": {"callee": [], "caller": ["fflush"]}, "fd_safer": {"callee": ["dup_safer", "<EXTERNAL>::__errno_location", "<EXTERNAL>::close", "<EXTERNAL>::__errno_location"], "caller": ["open_safer"]}, "__freading": {"callee": [], "caller": ["__freading"]}, "fputs_unlocked": {"callee": [], "caller": ["fputs_unlocked"]}, "main": {"callee": ["<EXTERNAL>::getpagesize", "set_program_name", "<EXTERNAL>::setlocale", "<EXTERNAL>::bindtextdomain", "<EXTERNAL>::textdomain", "atexit", "bad_cast", "bad_cast", "<EXTERNAL>::getopt_long", "<EXTERNAL>::gettext", "xdectoumax", "last_component", "quote", "<EXTERNAL>::gettext", "<EXTERNAL>::error", "usage", "<EXTERNAL>::gettext", "<EXTERNAL>::error", "usage", "<EXTERNAL>::gettext", "xdectoumax", "<EXTERNAL>::gettext", "<EXTERNAL>::error", "usage", "<EXTERNAL>::gettext", "xdectoumax", "<EXTERNAL>::gettext", "<EXTERNAL>::error", "usage", "<EXTERNAL>::gettext", "xdectoumax", "<EXTERNAL>::gettext", "<EXTERNAL>::error", "usage", "<EXTERNAL>::__ctype_b_loc", "to_uchar", "<EXTERNAL>::strncmp", "<EXTERNAL>::strncmp", "<EXTERNAL>::strchr", "parse_chunk", "<EXTERNAL>::gettext", "xdectoumax", "<EXTERNAL>::gettext", "<EXTERNAL>::error", "<EXTERNAL>::strcmp", "quote", "<EXTERNAL>::gettext", "<EXTERNAL>::error", "<EXTERNAL>::gettext", "<EXTERNAL>::error", "<EXTERNAL>::gettext", "<EXTERNAL>::error", "usage", "umaxtostr", "<EXTERNAL>::gettext", "<EXTERNAL>::error", "<EXTERNAL>::strlen", "<EXTERNAL>::strspn", "quote", "<EXTERNAL>::gettext", "<EXTERNAL>::gettext", "<EXTERNAL>::error", "usage", "<EXTERNAL>::gettext", "xdectoumax", "usage", "version_etc", "<EXTERNAL>::exit", "usage", "<EXTERNAL>::gettext", "<EXTERNAL>::error", "usage", "quote", "<EXTERNAL>::gettext", "<EXTERNAL>::error", "usage", "set_suffix_length", "quote", "<EXTERNAL>::gettext", "<EXTERNAL>::error", "usage", "<EXTERNAL>::strlen", "<EXTERNAL>::gettext", "<EXTERNAL>::error", "usage", "<EXTERNAL>::strcmp", "fd_reopen", "quotearg_style", "<EXTERNAL>::gettext", "<EXTERNAL>::__errno_location", "<EXTERNAL>::error", "xset_binary_mode", "fstat", "quotearg_n_style_colon", "<EXTERNAL>::__errno_location", "<EXTERNAL>::error", "io_blksize", "xmalloc", "ptr_align", "input_file_size", "quotearg_n_style_colon", "<EXTERNAL>::gettext", "<EXTERNAL>::__errno_location", "<EXTERNAL>::error", "umaxtostr", "quote", "<EXTERNAL>::gettext", "<EXTERNAL>::error", "<EXTERNAL>::sigemptyset", "<EXTERNAL>::sigaction", "<EXTERNAL>::sigaddset", "<EXTERNAL>::sigprocmask", "lines_split", "bytes_split", "line_bytes_split", "bytes_split", "bytes_chunk_extract", "lines_chunk_split", "lines_rr", "<EXTERNAL>::abort", "<EXTERNAL>::close", "quotearg_n_style_colon", "<EXTERNAL>::__errno_location", "<EXTERNAL>::error", "closeout", "<EXTERNAL>::__stack_chk_fail"], "caller": ["_start"]}, "xcharalloc": {"callee": ["xmalloc"], "caller": ["quotearg_n_options", "quotearg_alloc_mem"]}, "c_isupper": {"callee": [], "caller": []}, "FUN_00002020": {"callee": [], "caller": []}, "c_isalnum": {"callee": [], "caller": []}, "next_file_name": {"callee": ["<EXTERNAL>::strlen", "<EXTERNAL>::strlen", "xalloc_die", "xrealloc", "<EXTERNAL>::memcpy", "<EXTERNAL>::memset", "<EXTERNAL>::memcpy", "<EXTERNAL>::free", "xcalloc", "<EXTERNAL>::__assert_fail", "<EXTERNAL>::strlen", "<EXTERNAL>::memcpy", "<EXTERNAL>::gettext", "<EXTERNAL>::error"], "caller": ["cwrite", "lines_rr"]}, "create": {"callee": ["quotearg_style", "<EXTERNAL>::gettext", "<EXTERNAL>::fprintf", "open_safer", "fstat", "quotearg_style", "<EXTERNAL>::gettext", "<EXTERNAL>::__errno_location", "<EXTERNAL>::error", "quotearg_style", "<EXTERNAL>::gettext", "<EXTERNAL>::error", "<EXTERNAL>::ftruncate", "quotearg_n_style_colon", "<EXTERNAL>::gettext", "<EXTERNAL>::__errno_location", "<EXTERNAL>::error", "<EXTERNAL>::getenv", "<EXTERNAL>::setenv", "<EXTERNAL>::gettext", "<EXTERNAL>::__errno_location", "<EXTERNAL>::error", "quotearg_n_style_colon", "<EXTERNAL>::gettext", "<EXTERNAL>::fprintf", "<EXTERNAL>::pipe", "<EXTERNAL>::gettext", "<EXTERNAL>::__errno_location", "<EXTERNAL>::error", "<EXTERNAL>::fork", "<EXTERNAL>::close", "<EXTERNAL>::gettext", "<EXTERNAL>::__errno_location", "<EXTERNAL>::error", "<EXTERNAL>::close", "<EXTERNAL>::gettext", "<EXTERNAL>::__errno_location", "<EXTERNAL>::error", "<EXTERNAL>::dup2", "<EXTERNAL>::gettext", "<EXTERNAL>::__errno_location", "<EXTERNAL>::error", "<EXTERNAL>::close", "<EXTERNAL>::gettext", "<EXTERNAL>::__errno_location", "<EXTERNAL>::error", "<EXTERNAL>::sigprocmask", "last_component", "<EXTERNAL>::execl", "<EXTERNAL>::gettext", "<EXTERNAL>::__errno_location", "<EXTERNAL>::error", "<EXTERNAL>::gettext", "<EXTERNAL>::__errno_location", "<EXTERNAL>::error", "<EXTERNAL>::close", "<EXTERNAL>::gettext", "<EXTERNAL>::__errno_location", "<EXTERNAL>::error", "x2nrealloc", "<EXTERNAL>::__stack_chk_fail"], "caller": ["ofile_open", "cwrite"]}, "pipe": {"callee": [], "caller": ["pipe"]}, "__errno_location": {"callee": [], "caller": ["__errno_location"]}, "x2nrealloc": {"callee": ["xalloc_die", "xalloc_die", "xrealloc"], "caller": ["create", "x2realloc"]}, "safe_read": {"callee": ["<EXTERNAL>::read", "<EXTERNAL>::__errno_location", "<EXTERNAL>::__errno_location"], "caller": ["lines_chunk_split", "lines_split", "bytes_chunk_extract", "lines_rr", "line_bytes_split", "input_file_size", "bytes_split"]}, "quotearg_n_options": {"callee": ["<EXTERNAL>::__errno_location", "<EXTERNAL>::abort", "xalloc_die", "xrealloc", "<EXTERNAL>::memset", "quotearg_buffer_restyled", "<EXTERNAL>::free", "xcharalloc", "quotearg_buffer_restyled", "<EXTERNAL>::__errno_location"], "caller": ["quotearg_char_mem", "quotearg_n", "quotearg_n_style", "quotearg_n_style_colon", "quotearg_n_style_mem", "quote_n_mem", "quotearg_n_custom_mem", "quotearg_n_mem"]}, "strcmp": {"callee": [], "caller": ["strcmp"]}, "read": {"callee": [], "caller": ["read"]}, "set_custom_quoting": {"callee": ["<EXTERNAL>::abort"], "caller": ["quotearg_n_custom_mem"]}, "c_isalpha": {"callee": [], "caller": []}, "quotearg_custom_mem": {"callee": ["quotearg_n_custom_mem"], "caller": []}, "full_write": {"callee": ["safe_write", "<EXTERNAL>::__errno_location"], "caller": ["cwrite", "lines_chunk_split", "bytes_chunk_extract", "lines_rr"]}, "sigaction": {"callee": [], "caller": ["sigaction"]}, "memset": {"callee": [], "caller": ["memset"]}, "memmove": {"callee": [], "caller": ["memmove"]}, "lines_chunk_split": {"callee": ["<EXTERNAL>::__assert_fail", "<EXTERNAL>::memmove", "<EXTERNAL>::lseek", "quotearg_n_style_colon", "<EXTERNAL>::__errno_location", "<EXTERNAL>::error", "safe_read", "quotearg_n_style_colon", "<EXTERNAL>::__errno_location", "<EXTERNAL>::error", "<EXTERNAL>::memchr", "full_write", "<EXTERNAL>::gettext", "<EXTERNAL>::__errno_location", "<EXTERNAL>::error", "cwrite", "cwrite", "cwrite"], "caller": ["main"]}, "c_isascii": {"callee": [], "caller": []}, "dup_safer": {"callee": ["rpl_fcntl"], "caller": ["fd_safer"]}, "__ctype_b_loc": {"callee": [], "caller": ["__ctype_b_loc"]}, "sigaddset": {"callee": [], "caller": ["sigaddset"]}, "quotearg": {"callee": ["quotearg_n"], "caller": []}, "_start": {"callee": [], "caller": []}, "c_iscntrl": {"callee": [], "caller": []}, "c_isblank": {"callee": [], "caller": []}, "atexit": {"callee": [], "caller": ["main"]}, "fdopen": {"callee": [], "caller": ["fdopen"]}, "c_strcasecmp": {"callee": ["c_tolower", "c_tolower"], "caller": ["gettext_quote"]}, "error": {"callee": [], "caller": ["error"]}, "emit_mandatory_arg_note": {"callee": ["<EXTERNAL>::gettext", "<EXTERNAL>::fputs_unlocked"], "caller": ["usage"]}, "line_bytes_split": {"callee": ["safe_read", "quotearg_n_style_colon", "<EXTERNAL>::__errno_location", "<EXTERNAL>::error", "<EXTERNAL>::memrchr", "<EXTERNAL>::memrchr", "cwrite", "xrealloc", "cwrite", "cwrite", "xrealloc", "xalloc_die", "<EXTERNAL>::memcpy", "cwrite", "<EXTERNAL>::free"], "caller": ["main"]}, "xset_binary_mode_error": {"callee": [], "caller": ["xset_binary_mode"]}, "xset_binary_mode": {"callee": ["set_binary_mode", "xset_binary_mode_error"], "caller": ["main"]}, "last_component": {"callee": [], "caller": ["create", "main"]}, "register_tm_clones": {"callee": [], "caller": ["frame_dummy"]}, "c_islower": {"callee": [], "caller": []}, "clearerr_unlocked": {"callee": [], "caller": ["clearerr_unlocked"]}, "fwrite": {"callee": [], "caller": ["fwrite"]}, "__do_global_dtors_aux": {"callee": ["<EXTERNAL>::__cxa_finalize", "deregister_tm_clones"], "caller": ["__libc_csu_init"]}, "c_isprint": {"callee": [], "caller": []}, "_fini": {"callee": [], "caller": []}, "rpl_fcntl": {"callee": ["<EXTERNAL>::fcntl", "<EXTERNAL>::__errno_location", "rpl_fcntl", "rpl_fcntl", "<EXTERNAL>::fcntl", "<EXTERNAL>::fcntl", "<EXTERNAL>::__errno_location", "<EXTERNAL>::close", "<EXTERNAL>::__errno_location", "<EXTERNAL>::fcntl", "<EXTERNAL>::__stack_chk_fail"], "caller": ["rpl_fcntl", "dup_safer"]}, "__fpending": {"callee": [], "caller": ["__fpending"]}}