{"malloc": {"callee": [], "caller": ["dsa_decrypt_key"]}, "crypt_argchk": {"callee": [], "caller": ["dsa_decrypt_key"]}, "hash_is_valid": {"callee": [], "caller": ["dsa_decrypt_key"]}, "__stack_chk_fail": {"callee": [], "caller": ["dsa_decrypt_key"]}, "dsa_shared_secret": {"callee": [], "caller": ["dsa_decrypt_key"]}, "dsa_decrypt_key": {"callee": ["crypt_argchk", "crypt_argchk", "crypt_argchk", "crypt_argchk", "der_decode_sequence_ex", "find_hash_oid", "hash_is_valid", "malloc", "malloc", "free", "free", "der_decode_sequence_ex", "dsa_shared_secret", "hash_memory", "free", "free", "__stack_chk_fail"], "caller": []}, "hash_memory": {"callee": [], "caller": ["dsa_decrypt_key"]}, "find_hash_oid": {"callee": [], "caller": ["dsa_decrypt_key"]}, "free": {"callee": [], "caller": ["dsa_decrypt_key"]}, "der_decode_sequence_ex": {"callee": [], "caller": ["dsa_decrypt_key"]}}